procaliper/__init__.py
procaliper/_protein.py
procaliper/network.py
procaliper/protein_structure/__init__.py
procaliper/protein_structure/charge.py
procaliper/protein_structure/confidence.py
procaliper/protein_structure/cysteine_data.py
procaliper/protein_structure/distance.py
procaliper/protein_structure/sasa.py
procaliper/protein_structure/titration.py
procaliper/py.typed
procaliper/site_metadata/__init__.py
procaliper/site_metadata/custom_site_data.py
procaliper/site_metadata/uniprot_site_parsing.py
procaliper/type_aliases.py
procaliper/view/__init__.py
procaliper/view/nglview_utils.py
procaliper-0.2.1.dist-info/AUTHORS.md
procaliper-0.2.1.dist-info/LICENSE
procaliper-0.2.1.dist-info/METADATA
procaliper-0.2.1.dist-info/WHEEL
procaliper-0.2.1.dist-info/entry_points.txt
procaliper-0.2.1.dist-info/RECORD
