Metadata-Version: 2.3
Name: procaliper
Version: 0.2.1
Summary: Skeleton project created by Python Project Wizard (ppw).
License: GPL-3.0-only
Author: AlphaMeter
Author-email: song.feng@pnnl.gov
Requires-Python: >=3.9,<4.0
Classifier: Development Status :: 2 - Pre-Alpha
Classifier: Intended Audience :: Developers
Classifier: License :: OSI Approved :: GNU General Public License v3 (GPLv3)
Classifier: Natural Language :: English
Classifier: Programming Language :: Python :: 3
Classifier: Programming Language :: Python :: 3.9
Classifier: Programming Language :: Python :: 3.10
Classifier: Programming Language :: Python :: 3.11
Classifier: Programming Language :: Python :: 3.12
Classifier: Programming Language :: Python :: 3.13
Provides-Extra: dev
Provides-Extra: doc
Provides-Extra: pka
Provides-Extra: test
Provides-Extra: viz
Requires-Dist: biopandas (>=0.5.1,<1)
Requires-Dist: biopython (>=1.84,<2)
Requires-Dist: black (==24.8.0) ; extra == "dev"
Requires-Dist: distanceclosure (>=0.5.0)
Requires-Dist: flake8 (==7.1.1) ; extra == "dev"
Requires-Dist: flake8-docstrings (>=1.6.0,<2.0.0) ; extra == "dev"
Requires-Dist: isort (==5.10.1) ; extra == "dev"
Requires-Dist: matplotlib (>=3.8.0) ; extra == "viz"
Requires-Dist: mike (==2.1.2) ; extra == "doc"
Requires-Dist: mkdocs (==1.6.1) ; extra == "doc"
Requires-Dist: mkdocs-autorefs (==1.2.0) ; extra == "doc"
Requires-Dist: mkdocs-include-markdown-plugin (==6.2.2) ; extra == "doc"
Requires-Dist: mkdocs-material (==9.5.34) ; extra == "doc"
Requires-Dist: mkdocstrings (==0.26.1) ; extra == "doc"
Requires-Dist: mkdocstrings-python (==1.11.1) ; extra == "doc"
Requires-Dist: mypy (>=1.5.1,<2.0.0) ; extra == "dev"
Requires-Dist: networkx (>=3.1,<4)
Requires-Dist: nglview (>=3.0.8,<4) ; extra == "viz"
Requires-Dist: numpy (==1.26.4) ; extra == "pka"
Requires-Dist: openbabel-wheel (>=3.1.1.21)
Requires-Dist: pandas (>=2.2.2,<3.0.0)
Requires-Dist: pandas-stubs (>=2.2.2.240807,<3.0.0.0) ; extra == "dev"
Requires-Dist: pkai (==1.2.0) ; (python_full_version <= "3.11.0") and (extra == "pka")
Requires-Dist: pkginfo (>=1.9,<2.0) ; extra == "doc"
Requires-Dist: pre-commit (==3.8.0) ; extra == "dev"
Requires-Dist: propka (>=3.5.1,<4)
Requires-Dist: pypka (==2.10.0) ; extra == "pka"
Requires-Dist: pytest (==8.3.2) ; extra == "test"
Requires-Dist: pytest-cov (==5.0.0) ; extra == "test"
Requires-Dist: setuptools (==72.1.0) ; extra == "doc"
Requires-Dist: toml (>=0.10.2,<0.11.0) ; extra == "dev"
Requires-Dist: tox (==4.17.1) ; extra == "dev"
Requires-Dist: twine (==5.1.1) ; extra == "dev"
Requires-Dist: types-requests (>=2.31.0,<3.0.0) ; extra == "dev"
Requires-Dist: uniprot-id-mapper (>=1.1.2,<2)
Requires-Dist: virtualenv (>=20.0,<21.0) ; extra == "doc"
Project-URL: Homepage, https://github.com/LifeWorks/procaliper
